jsonframe/__init__.py
jsonframe/builders.py
jsonframe/fastapi.py
jsonframe/helpers.py
jsonframe/models.py
jsonframe/py.typed
jsonframe-0.1.2.dist-info/WHEEL
jsonframe-0.1.2.dist-info/METADATA
jsonframe-0.1.2.dist-info/RECORD
