Metadata-Version: 2.3
Name: jsonframe
Version: 0.1.2
Summary: A small, typed JSON frame (envelope) for API responses and messages.
Keywords: json,api,envelope,frame,schema,pydantic
Author: Rinat Advaer
Author-email: Rinat Advaer <rinat.advaer@gmail.com>
License: MIT License
Classifier: Development Status :: 2 - Pre-Alpha
Classifier: Intended Audience :: Developers
Classifier: License :: OSI Approved :: MIT License
Classifier: Programming Language :: Python :: 3
Classifier: Programming Language :: Python :: 3 :: Only
Classifier: Programming Language :: Python :: 3.10
Classifier: Programming Language :: Python :: 3.11
Classifier: Programming Language :: Python :: 3.12
Classifier: Typing :: Typed
Requires-Dist: pydantic>=2.12.5
Requires-Dist: fastapi>=0.100 ; extra == 'fastapi'
Requires-Dist: starlette>=0.27 ; extra == 'fastapi'
Requires-Python: >=3.10
Project-URL: Homepage, https://github.com/advaer/jsonframe
Project-URL: Repository, https://github.com/advaer/jsonframe
Project-URL: Issues, https://github.com/advaer/jsonframe/issues
Provides-Extra: fastapi
